pysipfenn/__init__.py
pysipfenn/core/__init__.py
pysipfenn/core/modelAdjusters.py
pysipfenn/core/modelExporters.py
pysipfenn/core/pysipfenn.py
pysipfenn/descriptorDefinitions/KS2022.py
pysipfenn/descriptorDefinitions/KS2022_dilute.py
pysipfenn/descriptorDefinitions/KS2022_randomSolutions.py
pysipfenn/descriptorDefinitions/README.md
pysipfenn/descriptorDefinitions/Ward2017.py
pysipfenn/descriptorDefinitions/__init__.py
pysipfenn/descriptorDefinitions/element_properties_Ward2017KS2022.csv
pysipfenn/descriptorDefinitions/labels_KS2022.csv
pysipfenn/descriptorDefinitions/labels_KS2022_dilute.csv
pysipfenn/descriptorDefinitions/labels_KS2022_randomSolutions.csv
pysipfenn/descriptorDefinitions/labels_Ward2017.csv
pysipfenn/descriptorDefinitions/property_names_Ward2017KS2022.txt
pysipfenn/descriptorDefinitions/assets/KS2022_randomSolution_ConvergencePlot.png
pysipfenn/misc/__init__.py
pysipfenn/misc/conveniences.py
pysipfenn/misc/prototypeLibrary.yaml
pysipfenn/modelsSIPFENN/README.md
pysipfenn/modelsSIPFENN/__init__.py
pysipfenn/modelsSIPFENN/models.json
pysipfenn/tests/__init__.py
pysipfenn/tests/test_AllCompatibleONNX_Ward2017.py
pysipfenn/tests/test_Core_prototypeLibrary.py
pysipfenn/tests/test_KS2022.py
pysipfenn/tests/test_KS2022_dilute.py
pysipfenn/tests/test_KS2022_randomSolutions.py
pysipfenn/tests/test_Krajewski2020_NN9NN20NN24_ONNX.py
pysipfenn/tests/test_ModelAdjusters.py
pysipfenn/tests/test_ModelExporters.py
pysipfenn/tests/test_Ward2017.py
pysipfenn/tests/test_customModel.py
pysipfenn/tests/test_pysipfenn.py
pysipfenn/tests/testCaseFiles/AdjusterTestDescriptors.csv
pysipfenn/tests/testCaseFiles/AdjusterTestDescriptors.npy
pysipfenn/tests/testCaseFiles/AdjusterTestTargets.csv
pysipfenn/tests/testCaseFiles/AdjusterTestTargets.npy
pysipfenn/tests/testCaseFiles/TestFile_DescriptorData_4_KS2022_labeled_enumerated.csv
pysipfenn/tests/testCaseFiles/TestFile_DescriptorData_4_KS2022_labeled_named.csv
pysipfenn-0.17.0.dist-info/licenses/LICENSE.md
pysipfenn-0.17.0.dist-info/METADATA
pysipfenn-0.17.0.dist-info/WHEEL
pysipfenn-0.17.0.dist-info/top_level.txt
pysipfenn-0.17.0.dist-info/RECORD
