Metadata-Version: 2.4
Name: pysipfenn
Version: 0.17.0
Summary: Python toolset for Structure-Informed Property and Feature Engineering with Neural Networks. It offers unique advantages through (1) effortless extensibility, (2) optimizations for ordered, dilute, and random atomic configurations, and (3) automated model tuning.
Author-email: Adam Krajewski <adam@phaseslab.org>, Jonathan Siegel <jwsiegel@tamu.edu>, Ricardo Amaral <rna5137@psu.edu>
Project-URL: Repository, https://git.pysipfenn.org
Project-URL: Homepage, https://pysipfenn.org
Project-URL: Bug Tracker, https://github.com/PhasesResearchLab/pySIPFENN/issues
Classifier: Programming Language :: Python :: 3
Classifier: Programming Language :: Python :: 3.10
Classifier: Programming Language :: Python :: 3.11
Classifier: Programming Language :: Python :: 3.12
Classifier: Programming Language :: Python :: 3.13
Classifier: Development Status :: 4 - Beta
Classifier: Intended Audience :: Science/Research
Classifier: License :: OSI Approved :: GNU Lesser General Public License v3 or later (LGPLv3+)
Classifier: Operating System :: OS Independent
Classifier: Topic :: Scientific/Engineering
Classifier: Topic :: Scientific/Engineering :: Artificial Intelligence
Classifier: Topic :: Scientific/Engineering :: Chemistry
Classifier: Topic :: Scientific/Engineering :: Physics
Requires-Python: >=3.10
License-File: LICENSE.md
Requires-Dist: pymatgen>=2024.2.20
Requires-Dist: spglib>=2.5.0
Requires-Dist: torch>=2.7.0
Requires-Dist: onnx2torch>=1.5.2
Requires-Dist: onnx>=1.13.0
Requires-Dist: numpy>=2.0.0
Requires-Dist: tqdm>=4.65.0
Requires-Dist: natsort>=8.3.0
Requires-Dist: pymongo>=4.4
Requires-Dist: pysmartdl2>=2.0.0
Requires-Dist: plotly>=5.15.0
Requires-Dist: dnspython
Requires-Dist: ruamel.yaml
Requires-Dist: colorama
Provides-Extra: dev
Requires-Dist: coremltools>=7.0; extra == "dev"
Requires-Dist: onnxconverter_common>=1.14.0; extra == "dev"
Requires-Dist: onnxsim==0.4.33; extra == "dev"
Requires-Dist: onnxscript; extra == "dev"
Requires-Dist: onnxruntime>=1.20.0; extra == "dev"
Requires-Dist: optimade[http_client]>=1.0.0; extra == "dev"
Provides-Extra: test
Requires-Dist: pytest>=7.0.0; extra == "test"
Requires-Dist: flask>=2.0.0; extra == "test"
Dynamic: license-file
